systemctl_mqtt/__init__.py
systemctl_mqtt/_dbus.py
systemctl_mqtt/_homeassistant.py
systemctl_mqtt/_mqtt.py
systemctl_mqtt/_utils.py
systemctl_mqtt/_dbus/__init__.py
systemctl_mqtt/_dbus/login_manager.py
systemctl_mqtt/_dbus/service_manager.py
systemctl_mqtt-1.2.0.dist-info/COPYING
systemctl_mqtt-1.2.0.dist-info/METADATA
systemctl_mqtt-1.2.0.dist-info/WHEEL
systemctl_mqtt-1.2.0.dist-info/entry_points.txt
systemctl_mqtt-1.2.0.dist-info/top_level.txt
systemctl_mqtt-1.2.0.dist-info/RECORD
