Metadata-Version: 2.1
Name: systemctl-mqtt
Version: 1.2.0
Summary: MQTT client triggering & reporting shutdown on systemd-based systems
Home-page: https://github.com/fphammerle/systemctl-mqtt
Author: Fabian Peter Hammerle
Author-email: fabian@hammerle.me
License: GPLv3+
Project-URL: Changelog, https://github.com/fphammerle/systemctl-mqtt/blob/master/CHANGELOG.md
Keywords: IoT,automation,home-assistant,home-automation,lock,mqtt,shutdown,systemd
Classifier: Development Status :: 4 - Beta
Classifier: Intended Audience :: End Users/Desktop
Classifier: Intended Audience :: System Administrators
Classifier: License :: OSI Approved :: GNU General Public License v3 or later (GPLv3+)
Classifier: Operating System :: POSIX :: Linux
Classifier: Programming Language :: Python :: 3.9
Classifier: Programming Language :: Python :: 3.10
Classifier: Programming Language :: Python :: 3.11
Classifier: Programming Language :: Python :: 3.12
Classifier: Programming Language :: Python :: 3.13
Classifier: Topic :: Home Automation
Requires-Python: >=3.9
License-File: COPYING
Requires-Dist: aiomqtt (<3,>=2)
Requires-Dist: jeepney (<1.0,>=0.8)
